MANIFEST.in
README.md
requirements.txt
setup.py
one_two_scrape.egg-info/PKG-INFO
one_two_scrape.egg-info/SOURCES.txt
one_two_scrape.egg-info/dependency_links.txt
one_two_scrape.egg-info/requires.txt
one_two_scrape.egg-info/top_level.txt
otscrape/__init__.py
otscrape/core/__init__.py
otscrape/core/buffer.py
otscrape/core/magics.py
otscrape/core/pandas.py
otscrape/core/util.py
otscrape/core/base/__init__.py
otscrape/core/base/buffer.py
otscrape/core/base/data_model.py
otscrape/core/base/exception.py
otscrape/core/base/exporter.py
otscrape/core/base/extractor.py
otscrape/core/base/loader.py
otscrape/core/base/share.py
otscrape/core/base/state.py
otscrape/core/base/wrapper.py
otscrape/core/base/abstract/__init__.py
otscrape/core/base/abstract/nofail.py
otscrape/core/base/abstract/willfail.py
otscrape/core/base/page/__init__.py
otscrape/core/base/page/page.py
otscrape/core/base/worker/__init__.py
otscrape/core/base/worker/executor.py
otscrape/core/base/worker/pool.py
otscrape/core/base/worker/worker.py
otscrape/core/exporter/__init__.py
otscrape/core/exporter/file/__init__.py
otscrape/core/exporter/file/base.py
otscrape/core/exporter/file/json.py
otscrape/core/extractor/__init__.py
otscrape/core/extractor/chain.py
otscrape/core/extractor/dict.py
otscrape/core/extractor/json.py
otscrape/core/extractor/lambda_.py
otscrape/core/extractor/map.py
otscrape/core/extractor/raw.py
otscrape/core/extractor/request.py
otscrape/core/extractor/soup.py
otscrape/core/extractor/xpath.py
otscrape/core/extractor/file/__init__.py
otscrape/core/extractor/file/file.py
otscrape/core/extractor/file/line.py
otscrape/core/extractor/nested/__init__.py
otscrape/core/extractor/nested/zip_dict.py
otscrape/core/extractor/text/__init__.py
otscrape/core/extractor/text/etree.py
otscrape/core/extractor/text/json.py
otscrape/core/extractor/text/regex.py
otscrape/core/extractor/text/soup.py
otscrape/core/loader/__init__.py
otscrape/core/loader/dummy.py
otscrape/core/loader/file/__init__.py
otscrape/core/loader/file/csv.py
otscrape/core/loader/file/file.py
otscrape/core/loader/file/json.py
otscrape/core/loader/file/reader.py
otscrape/core/loader/file/result.py
